globalomnium/__init__.py
globalomnium/__main__.py
globalomnium/cli.py
globalomnium/client.py
globalomnium/go_types.py
globalomnium/mqtt.py
globalomnium/parsers.py
globalomnium-2024.10.0.dist-info/LICENSE
globalomnium-2024.10.0.dist-info/METADATA
globalomnium-2024.10.0.dist-info/WHEEL
globalomnium-2024.10.0.dist-info/entry_points.txt
globalomnium-2024.10.0.dist-info/top_level.txt
globalomnium-2024.10.0.dist-info/RECORD
