Metadata-Version: 2.1
Name: globalomnium
Version: 2024.10.0
Summary: Interface to globalomnium.com water data
Home-page: https://github.com/carlos-48/globalomnium
Author: carlos-48
Author-email: karloselmaster@gmail.com
Project-URL: Bug Tracker, https://github.com/carlos-48/globalomnium/issues
Classifier: Programming Language :: Python :: 3
Classifier: License :: OSI Approved :: MIT License
Classifier: Operating System :: OS Independent
Requires-Python: >=3.9
License-File: LICENSE
Requires-Dist: aiohttp<4,>=3.8.0
Provides-Extra: mqtt
Requires-Dist: paho-mqtt<2,>=1.6.1; extra == "mqtt"
